{
  "task": "T_C",
  "condition": "PosOnly",
  "round": 2,
  "exit_code": 0,
  "duration_sec": 3.264296,
  "output_exists": true,
  "useful": false,
  "diag": {
    "all_finite": false,
    "n_nan": 3072,
    "useful": false,
    "reason": "non-finite or unbounded"
  },
  "stderr_tail": "  return ufunc(a, fct, axes=[(axis,), (), (axis,)], out=out)\n/stage2/runs/T_C/PosOnly/round2/candidate.py:107: RuntimeWarning: invalid value encountered in multiply\n  return np.fft.ifft(ik * np.fft.fft(f_arr)).real\n/stage2/runs/T_C/PosOnly/round2/candidate.py:140: RuntimeWarning: overflow encountered in multiply\n  rhs_v_nl = -6.0 * v_arr * spectral_dx(v_arr) - spectral_dx(u_arr * v_arr)"
}